{
  "fill" : "automatic",
  "groups" : [
    {
      "blur-material-specializations" : [
        {
          "value" : 0.5
        },
        {
          "appearance" : "dark",
          "value" : 0.5
        }
      ],
      "hidden" : false,
      "layers" : [
        {
          "blend-mode-specializations" : [
            {
              "value" : "normal"
            },
            {
              "appearance" : "tinted",
              "value" : "normal"
            }
          ],
          "fill-specializations" : [
            {
              "value" : "automatic"
            },
            {
              "appearance" : "dark",
              "value" : {
                "solid" : "gray:1.00000,1.00000"
              }
            },
            {
              "appearance" : "tinted",
              "value" : {
                "solid" : "gray:0.73105,1.00000"
              }
            }
          ],
          "glass" : true,
          "hidden" : false,
          "image-name" : "Normal.svg",
          "name" : "Normal",
          "opacity-specializations" : [
            {
              "appearance" : "tinted",
              "value" : 0.75
            }
          ]
        }
      ],
      "opacity-specializations" : [
        {
          "appearance" : "tinted",
          "value" : 1
        }
      ],
      "shadow-specializations" : [
        {
          "value" : {
            "kind" : "layer-color",
            "opacity" : 0.5
          }
        },
        {
          "appearance" : "dark",
          "value" : {
            "kind" : "layer-color",
            "opacity" : 1
          }
        }
      ],
      "specular" : true,
      "translucency-specializations" : [
        {
          "value" : {
            "enabled" : true,
            "value" : 0.2
          }
        },
        {
          "appearance" : "dark",
          "value" : {
            "enabled" : true,
            "value" : 0.2
          }
        }
      ]
    }
  ],
  "supported-platforms" : {
    "circles" : [
      "watchOS"
    ],
    "squares" : "shared"
  }
}